swift_iso20022_toolbox/__init__.py
swift_iso20022_toolbox/aggregate_metadata.py
swift_iso20022_toolbox/extract_xsd_versions.py
swift_iso20022_toolbox/iso20022_toolbox.py
swift_iso20022_toolbox/xml_to_xpath.py
swift_iso20022_toolbox/xml_to_xpath_v2.py
swift_iso20022_toolbox-0.1.0.dist-info/METADATA
swift_iso20022_toolbox-0.1.0.dist-info/WHEEL
swift_iso20022_toolbox-0.1.0.dist-info/entry_points.txt
swift_iso20022_toolbox-0.1.0.dist-info/top_level.txt
swift_iso20022_toolbox-0.1.0.dist-info/RECORD
