Metadata-Version: 2.4
Name: swift-iso20022-toolbox
Version: 0.1.0
Summary: Streamlit-based toolbox for uploading, parsing, and aggregating ISO 20022 payment message files (CSV, XML, Excel, XSD)
Home-page: https://github.com/yousdin/swift-iso20022-payment-mt2mx-toolbox
Author: Yous Guil
License: MIT
Classifier: Programming Language :: Python :: 3
Classifier: License :: OSI Approved :: MIT License
Classifier: Operating System :: OS Independent
Requires-Python: >=3.7
Requires-Dist: streamlit
Requires-Dist: pandas
Requires-Dist: openpyxl
Requires-Dist: xlsxwriter
Dynamic: author
Dynamic: classifier
Dynamic: description
Dynamic: description-content-type
Dynamic: home-page
Dynamic: license
Dynamic: requires-dist
Dynamic: requires-python
Dynamic: summary
